LICENSE
MANIFEST.in
README.rst
requirements.txt
setup.cfg
setup.py
flask_restler/__init__.py
flask_restler/api.py
flask_restler/auth.py
flask_restler/fields.py
flask_restler/filters.py
flask_restler/mongo.py
flask_restler/peewee.py
flask_restler/resource.py
flask_restler/runner.py
flask_restler/sqlalchemy.py
flask_restler/templates/swagger.html
flask_restler_pw3.egg-info/PKG-INFO
flask_restler_pw3.egg-info/SOURCES.txt
flask_restler_pw3.egg-info/dependency_links.txt
flask_restler_pw3.egg-info/requires.txt
flask_restler_pw3.egg-info/top_level.txt