Metadata-Version: 1.1
Name: flask-restler-pw3
Version: 0.0.1
Summary: Build REST API for Flask using Marshmallow.
Home-page: https://github.com/jianc65/flask-restler
Author: Kirill Klenov
Author-email: horneds@gmail.com
License: UNKNOWN
Keywords: flask,marshmallow,rest,api
Platform: Any
Classifier: Development Status :: 4 - Beta
Classifier: Intended Audience :: Developers
Classifier: License :: OSI Approved :: BSD License
Classifier: Natural Language :: English
Classifier: Natural Language :: Russian
Classifier: Operating System :: OS Independent
Classifier: Programming Language :: Python :: 2
Classifier: Programming Language :: Python :: 3
Classifier: Programming Language :: Python
Classifier: Topic :: Software Development :: Libraries :: Python Modules
Classifier: Topic :: Software Development :: Testing
Classifier: Topic :: Utilities
